graphqlpy/__init__.py
graphqlpy/field.py
graphqlpy-0.0.1.dist-info/DESCRIPTION.rst
graphqlpy-0.0.1.dist-info/METADATA
graphqlpy-0.0.1.dist-info/RECORD
graphqlpy-0.0.1.dist-info/WHEEL
graphqlpy-0.0.1.dist-info/metadata.json
graphqlpy-0.0.1.dist-info/top_level.txt
