Metadata-Version: 2.0
Name: graphqlpy
Version: 0.0.1
Summary: A humble attempt at a library generating GraphQL queries programatically.
Home-page: https://github.com/seporaitis/graphqlpy
Author: Julius Seporaitis
Author-email: julius@seporaitis.net
License: MIT
Keywords: graphql
Platform: UNKNOWN
Classifier: Development Status :: 3 - Alpha
Classifier: Intended Audience :: Developers
Classifier: License :: OSI Approved :: MIT License
Classifier: Natural Language :: English
Classifier: Programming Language :: Python :: 3.6
